wordpredict/__init__.py
wordpredict/utils.py
wordpredict/wordpredict.py
wordpredict-0.2.3.dist-info/METADATA
wordpredict-0.2.3.dist-info/WHEEL
wordpredict-0.2.3.dist-info/RECORD
