Metadata-Version: 2.1
Name: wordpredict
Version: 0.2.3
Summary: word predictor
Home-page: https://github.com/2ndr9/wordpredict
Author: 2ndr9
Requires-Python: >=3.9,<4.0
Classifier: Programming Language :: Python :: 3
Classifier: Programming Language :: Python :: 3.9
Classifier: Programming Language :: Python :: 3.10
Classifier: Programming Language :: Python :: 3.11
Classifier: Programming Language :: Python :: 3.12
Project-URL: Repository, https://github.com/2ndr9/wordpredict
